<video youtube="1.00:JWGFMTCUDK8" url_name="92918502171a4c359fdac0accda24876" display_name="The Clausius Clapeyron Relation" download_track="true" download_video="true" edx_video_id="IITME2092014-V019200" html5_sources="[&quot;https://d2f1egay8yehza.cloudfront.net/IITME209/IITME2092014-V019200_DTH.mp4&quot;]" sub="IITME2092014-V019200_DTH" youtube_id_0_75="" youtube_id_1_0="JWGFMTCUDK8" youtube_id_1_25="" youtube_id_1_5="">
  <source src="https://d2f1egay8yehza.cloudfront.net/IITME209/IITME2092014-V019200_DTH.mp4"/>
  <video_asset client_video_id="ME209x_S210_The_Clausius_Clapeyron_Relation_IIT_Bombay" duration="696.81">
    <encoded_video bitrate="174" file_size="15194859" profile="mobile_high" url="https://d2f1egay8yehza.cloudfront.net/IITME209/IITME2092014-V019200_MB1.mp4"/>
    <encoded_video bitrate="127" file_size="11097253" profile="mobile_low" url="https://d2f1egay8yehza.cloudfront.net/IITME209/IITME2092014-V019200_MB2.mp4"/>
    <encoded_video bitrate="1000" file_size="31219722" profile="desktop_mp4" url="https://d2f1egay8yehza.cloudfront.net/IITME209/IITME2092014-V019200_DTH.mp4"/>
    <encoded_video bitrate="1000" file_size="93500542" profile="desktop_webm" url="https://d2f1egay8yehza.cloudfront.net/IITME209/IITME2092014-V019200_DTH.webm"/>
    <encoded_video bitrate="0" file_size="0" profile="audio_mp3" url="https://d2f1egay8yehza.cloudfront.net/IITME209/IITME2092014-V019200_AUD.mp3"/>
  </video_asset>
</video>
